{
  "url": "https://www.bayika.de/de/mitgliedschaft-und-listen/listeneintragung/",
  "fingerprint": "baabd275e2a129b991e7990211125f374907e703ce4b4231929adaf3f82ef22c",
  "lastChecked": "2026-05-17",
  "lastChanged": "2026-05-17",
  "statusHistory": [
    {
      "status": "UNCHANGED",
      "date": "2026-04-30"
    },
    {
      "status": "CHANGED",
      "date": "2026-05-03"
    },
    {
      "status": "CHANGED",
      "date": "2026-05-10"
    },
    {
      "status": "CHANGED",
      "date": "2026-05-17"
    }
  ]
}
